{
  "application": {
    "handle": "com.venul.region72",
    "version_name": "1.018",
    "version_code": "18",
    "uaid": "4CED5C49F968DB43BEA6A182A529818EDD74E3CA",
    "name": "\u041c\u043e\u0439 \u0442\u0435\u0440\u0430\u043f\u0435\u0432\u0442 72",
    "permissions": [
      "android.permission.WRITE_EXTERNAL_STORAGE",
      "android.permission.BODY_SENSORS",
      "android.permission.WAKE_LOCK",
      "android.permission.ACCESS_FINE_LOCATION",
      "android.permission.BLUETOOTH_ADMIN",
      "android.permission.INTERNET",
      "android.permission.ACCESS_NETWORK_STATE",
      "android.permission.READ_EXTERNAL_STORAGE",
      "android.permission.ACTIVITY_RECOGNITION",
      "com.google.android.finsky.permission.BIND_GET_INSTALL_REFERRER_SERVICE",
      "android.permission.BLUETOOTH"
    ],
    "libraries": [
      "org.apache.http.legacy"
    ]
  },
  "apk": {
    "path": "apks/com.venul.region72.apk",
    "checksum": "e7873b6fab4395d4d3736b8009f8fdab90b175df877bef66029abefd69350afe"
  },
  "trackers": [
    {
      "name": "Google CrashLytics",
      "id": 27
    },
    {
      "name": "Google Firebase Analytics",
      "id": 49
    }
  ]
}