{
  "application": {
    "handle": "ru.alfacapital.lk",
    "version_name": "2.64.0",
    "version_code": "696",
    "uaid": "841255F64A25386DE89D4BD96C5FBCC50C3B754D",
    "name": "\u0410\u043b\u044c\u0444\u0430 \u041a\u0430\u043f\u0438\u0442\u0430\u043b",
    "permissions": [
      "android.permission.USE_FINGERPRINT",
      "android.permission.WRITE_EXTERNAL_STORAGE",
      "android.permission.SET_ANIMATION_SCALE",
      "ru.alfacapital.lk.permission.PROCESS_PUSH_MSG",
      "com.android.vending.CHECK_LICENSE",
      "android.permission.VIBRATE",
      "android.permission.FOREGROUND_SERVICE",
      "android.permission.USE_BIOMETRIC",
      "android.permission.ACCESS_WIFI_STATE",
      "android.permission.RECEIVE_BOOT_COMPLETED",
      "ru.alfacapital.lk.permission.pushserver.RECEIVE",
      "android.permission.WAKE_LOCK",
      "android.permission.INTERNET",
      "android.permission.CAMERA",
      "android.permission.READ_PHONE_STATE",
      "android.permission.READ_EXTERNAL_STORAGE",
      "android.permission.ACCESS_NETWORK_STATE",
      "com.google.android.finsky.permission.BIND_GET_INSTALL_REFERRER_SERVICE",
      "com.google.android.c2dm.permission.RECEIVE",
      "ru.alfacapital.lk.permission.PUSH_PROVIDER",
      "android.permission.READ_CLIPBOARD"
    ],
    "libraries": [
      "org.apache.http.legacy",
      "androidx.window.extensions",
      "androidx.window.sidecar"
    ]
  },
  "apk": {
    "path": "apks/ru.alfacapital.lk.apk",
    "checksum": "a288bbf2c59812f571fff935692c1c3391f754b3bdf9519fc2dc8a84d8e51308"
  },
  "trackers": [
    {
      "name": "AppsFlyer",
      "id": 12
    },
    {
      "name": "Google CrashLytics",
      "id": 27
    },
    {
      "name": "Google Firebase Analytics",
      "id": 49
    },
    {
      "name": "Facebook Analytics",
      "id": 66
    },
    {
      "name": "Facebook Login",
      "id": 67
    },
    {
      "name": "Facebook Share",
      "id": 70
    },
    {
      "name": "AppMetrica",
      "id": 140
    },
    {
      "name": "Huawei Mobile Services (HMS) Core",
      "id": 333
    }
  ]
}